{"pubsub.common":{"yes.button":"HIja'","no.button":"Qo'","cancel.button":"qIl","ok.button":"lu'","save.button":"choq","apply.button":"apply choH","Actions.label":"vanglu'Qo'DI'","Edit.label":"Edit","Delete.label":"Delete","Enable.label":"Enable","Configuration.title":"configuration","Publisher.title":"publisher","Subscriber.title":"subscriber"},"pubsub.addPubsub":{"AddPubsub.label":"chel publisher","Connection.label":"connection","WriterGroup.label":"qonwI' ghom","Writer.label":"qonwI'","DataSet.label":"De' Set","Setup.label":"Setup","Reader.label":"laDwI'","ReaderGroup.label":"laDwI' ghom"},"pubsub.config":{"Publisher.label":"publisher","Subscriber.label":"subscriber","Connection.label":"connection"},"pubsub.publisher":{"AddPublisher.label":"chel publisher","NoPublisher.label":"pagh publisher configured","Name.label":"pong","Connection.label":"connection","PublishingInertval.label":"Publishing Interval","Address.label":"ghoch SoQ","Interface.label":"interface","PublishedMessages.label":"Published Messages","State.label":"Sep","Status.label":"Dotlh","Actions.label":"vanglu'Qo'DI'","PublisherId.label":"Publisher ID","delete.label":"Delete","enable.label":"Enable","edit.label":"Edit","FieldName.label":"yotlh pong","PublishNodePath.label":"Data Layer SoQ","DataType.label":"De' Segh","delete.Confirmation":"delete DaneHbej'a' {{value}}?","deletePublisher":"Delete Publisher","enable.Confirmation":"enable DaneH'a' {{value}}?","enablePublisher":"Enable Publisher","pubsubConfiguration.title":"OPC UA Pub/Sub configuration","readOnlyPermission":"Qu'vam Data' 'e' chaw' Daghajbe'","id.label":"ID","id.toolTip":"publisher ID, writer ghom ID, De' set writer ID"},"pubsub.addConnection":{"AddConnection.label":"chel connection","Connection.label":"connection pong","PublisherIDType.label":"publisher ID Segh","PublisherID.label":"Publisher ID","CommunicationType.label":"Qum Segh","Address.label":"SoQ","AddressNetworkInterface.label":"SoQ Network Interface","ExpertProperties.label":"po' Properties"},"pubsub.calloutNotification":{"publisherUpdateSuccess.text":"OPC UA Publisher details updated successfully","subscriberUpdateSuccess.text":"OPC UA Subscriber details updated successfully","AppliedChangesSuccess.text":"Qapchu' publisher 'ej subscriber De' toD","NoConfigLoaded.text":"pagh configuration De' loaded","NoSessionData.text":"pagh session De' tu'lu'","ReaderGroupNotFound.text":"ghom {{value}} tu'lu'be'","ReaderNotFound.text":"laDwI{{value}} tu'lu'be'","WriterNotFound.text":"qonwI' {{value}} tu'lu'be'","WriterGroupNotFound.text":"writergroup {{value}} tu'lu'","ConnectionNotFound.text":"connection {{value}} tu'lu'be'"},"pubsub.addPublisher":{"AddPubsub.label":"chel publisher","Connection.label":"connection pong","WriterName.label":"qonwI' pong","Address.label":"SoQ"},"pubsub.writerGroup":{"WriterGroupName.label":"qonwI' ghom pong","WriterGroupId.label":"qonwI' ghom ID","PublishingInterval.label":"Publishing Interval","SecurityMode.label":"Hung Mode","MaxNetworkMessageSize.label":"max Network QIn Size","KeepAliveTime.label":"yIntaH poH","HeaderLayout.label":"Header Layout","AddWriterGroup.label":"chel qonwI' ghom"},"pubsub.writer":{"WriterName.label":"qonwI' pong","DataSetWriterId.label":"Data Set Writer ID","DataSetEncoding.label":"HablI' encoding"},"pubsub.dataSet":{"NoDataSetConfigured.label":"pagh De' setup configured","AddDataSet.label":"chel De' Set","FieldName.label":"yotlh pong","PublishedNodePath.label":"Published Node Path","DataType.label":"De' Segh"},"pubsub.AdddataSet":{"AddDataSet.label":"chel item De' Set","EditDataSet.label":"Edit De' set item","PathError.label":"He poQlu'","Path.label":"He"},"pubsub.Subscriber":{"NoSubscriber.label":"pagh subscriber configured","AddSubscriber.label":"chel subscriber","Name.label":"pong","TargetedPublisherId.label":"Targeted Publisher ID","TargetedWriterGroupId.label":"Targeted Writer Group ID","TargetedDataSetWriterId.label":"Targeted Data Set Writer ID","Address.label":"SoQ","ReceivedMessages.label":"QIn Hev","State.label":"Sep","Status.label":"Dotlh","TargetNodePath.label":"DoS node path","MirroredNodePath.label":"neSlo' node path","DataType.label":"De' Segh","delete.Confirmation":"delete DaneHbej'a' {{value}}?","deleteSubscriber":"Delete Subscriber","enable.Confirmation":"enable DaneH'a' {{value}}?","enableSubscriber":"Enable Subscriber","id.toolTip":"publisher ID, writer ghom ID, De' set writer ID"},"pubsub.appNotInit":{"appInitializing":"DaH initialized app. chaq yapnIS poH ghItlhvetlh yIraDmoH.","description":"ghaytan wa' meq:","error.header":"DaH Hutlh OPC UA Pub/Sub app.","noPermission":"ghItlhvam DaleghmeH chaw' Daghajbe'.","refresh":"yIraDmoH","servicemode":"DaH active \"Service\" mode. DubelmoHchugh \"Operation Mode\" {{value}} 'ej yInIDqa'.","servicemode.appManagerLink":"App vu'wI'","details_1":"DubelmoHchugh check","details_2":"De' chel","Logbook":"QonoS"},"pubsub.readerGroup":{"Name.label":"pong","writerGroupId.label":"qonwI' ghom ID","dataSetWriterId.label":"Data Set Writer ID","publishingInterval.label":"Publishing Interval"},"pubsub.reader":{"Name.label":"pong","maxNetworkMessageSize.label":"max Network QIn Size"},"pubsub.ConfigTab":{"ID.header":"ID","State.header":"Sep","Progress.header":"Ser","Diagnosis.header":"Diagnosis","Action.header":"vang","View.tooltip":"View Configuration","Delete.tooltip":"Delete Configuration","Add.tooltip":"chel configuration","deleteConfig.text":"delete '{{value}}'","deletedConfig.text":"configuration \"{{value}}\" successfully deleted","delete.description":"SIbI' configuration node deleted 'oH. ta'vam ta'Ha'laH pagh.","loadConfiguration.label":"Load Configuration","validJSON.label":"valid json","inValidJSON.label":"Invalid JSON","configurationSuccess.label":"Qapchu' configuration toD","configuratioFailure.label":"luj toD configuration"}}