{"configuration.vpn-manager.description":"VPN configuration De'","settings.vpn.title":"vpn","settings.vpn.description":"virtual private network cher","licenses.SWL-XCx-VPN-VPNCLIENTxxxx-NNNN.title":"ctrlx os chaw' - VPN Client","licenses.SWL-XCx-VPN-VPNCLIENTxxxx-NNNN.description":"vpn Client Qutlh openvpn 'ej ipsec for ctrlx os","licenses.SWL-XCx-VPN-VPNCLIENTxRSA-NNNN.title":"ctrlx os chaw' - vpn Client rsa Extension (add-on)","licenses.SWL-XCx-VPN-VPNCLIENTxRSA-NNNN.description":"vpn client add-on lo' rsa functionality.","scopes-declaration.rexroth-vpnmanager.web.name":"vpn","scopes-declaration.rexroth-vpnmanager.web.description":"cher 'ej vu' Virtual Private Networks (VPNs)","scopes-declaration.rexroth-vpnmanager.web.all.rwx.name":"vu'","scopes-declaration.rexroth-vpnmanager.web.all.rwx.description":"connections vu'","scopes-declaration.rexroth-vpnmanager.web.connections.rx.name":"Qap","scopes-declaration.rexroth-vpnmanager.web.connections.rx.description":"start 'ej mev connections","scopes-declaration.rexroth-vpnmanager.web.all.r.name":"legh","scopes-declaration.rexroth-vpnmanager.web.all.r.description":"View connection details","certificatestores.vpnmanager.title":"VPN Client","certificatestores.vpnmanager.description":"ngaQHa'moHwI'mey certificates je poQ vpn client","documentation.vpnmanager.description":"Provides functionality for configuring a VPN client (OpenVPN, IPSec)."}